cura/core/__init__.py
cura/core/util.py
cura/core/cli/__init__.py
cura-0.0.2.dist-info/entry_points.txt
cura-0.0.2.dist-info/WHEEL
cura-0.0.2.dist-info/METADATA
cura-0.0.2.dist-info/RECORD
